idict/__init__.py
idict/config.py
idict/core/__init__.py
idict/core/appearance.py
idict/core/frozenidentifieddict.py
idict/core/identification.py
idict/core/idict_.py
idict/core/iempty.py
idict/core/rshift.py
idict/data/__init__.py
idict/data/compression.py
idict/data/load.py
idict/data/serialization.py
idict/function/__init__.py
idict/function/data.py
idict/function/dataset.py
idict/function/evaluation.py
idict/function/manipulation.py
idict/function/model.py
idict/function/text.py
idict/function/vizualization.py
idict/function/wrapper.py
idict/macro/__init__.py
idict/macro/data.py
idict/macro/evaluation.py
idict/macro/higherorder.py
idict/parameter/__init__.py
idict/parameter/ifunctionspace.py
idict/parameter/ilet.py
idict/persistence/__init__.py
idict/persistence/cache.py
idict/persistence/cached.py
idict/persistence/compressedcache.py
idict/persistence/disk.py
idict/persistence/locker.py
idict/persistence/shelchemy.py
idict/persistence/sqla.py
idict-4.220518.13.dist-info/LICENSE
idict-4.220518.13.dist-info/METADATA
idict-4.220518.13.dist-info/WHEEL
idict-4.220518.13.dist-info/RECORD
