Metadata-Version: 2.1
Name: idict
Version: 4.220518.13
Summary: Lazy dict with predictable deterministic universally unique identifiers
License: GPL
Author: davips
Author-email: dpsabc@gmail.com
Requires-Python: >=3.8,<3.10
Classifier: License :: Other/Proprietary License
Classifier: Programming Language :: Python :: 3
Classifier: Programming Language :: Python :: 3.8
Classifier: Programming Language :: Python :: 3.9
Provides-Extra: full
Requires-Dist: SQLAlchemy (>=1.4.27,<2.0.0) ; extra == "full"
Requires-Dist: bson (>=0.5.10,<0.6.0)
Requires-Dist: dill (>=0.3.5,<0.4.0)
Requires-Dist: garoupa (>=2.220128.1,<3.0.0)
Requires-Dist: ldict (>=3.220128.4,<4.0.0)
Requires-Dist: liac-arff (>=2.5.0,<3.0.0)
Requires-Dist: lz4 (>=4.0.0,<5.0.0)
Requires-Dist: orjson (>=3.5.0,<4.0.0)
Requires-Dist: pandas (==1.3.4) ; extra == "full"
Requires-Dist: pip (>=21.3.1,<22.0.0)
Requires-Dist: scikit-learn (==1.0.1) ; extra == "full"
Requires-Dist: temporenc (>=0.1.0,<0.2.0)
